DrawVennDiagram/__init__.py
DrawVennDiagram-0.6.0.dist-info/LICENSES.txt
DrawVennDiagram-0.6.0.dist-info/METADATA
DrawVennDiagram-0.6.0.dist-info/WHEEL
DrawVennDiagram-0.6.0.dist-info/top_level.txt
DrawVennDiagram-0.6.0.dist-info/RECORD
