Metadata-Version: 2.1
Name: DrawVennDiagram
Version: 0.6.0
Summary: Python API for visualisation of sets.
Home-page: UNKNOWN
Author: Nathan Crowley
Author-email: crowley2305@gmail.com
License: MIT
Platform: UNKNOWN
Classifier: Development Status :: 1 - Planning
Classifier: Intended Audience :: Education
Classifier: Operating System :: POSIX :: Linux
Classifier: License :: OSI Approved :: MIT License
Classifier: Programming Language :: Python :: 3
Requires-Dist: matplotlib
Requires-Dist: matplotlib-venn
